bids_json/__init__.py
bids_json/consolidate_json_phenos.py
bids_json_consolidation-0.0.1.dist-info/LICENSE
bids_json_consolidation-0.0.1.dist-info/METADATA
bids_json_consolidation-0.0.1.dist-info/WHEEL
bids_json_consolidation-0.0.1.dist-info/top_level.txt
bids_json_consolidation-0.0.1.dist-info/RECORD
