Metadata-Version: 2.1
Name: bids-json-consolidation
Version: 0.0.1
Summary: A simple package for consolidating BIDS formatted JSON data
Home-page: https://github.com/marconardin/bids-json
Author: Marco Nardin
Author-email: 27.marco@gmail.com
License: UNKNOWN
Platform: UNKNOWN
Classifier: Programming Language :: Python :: 2.7
Classifier: Programming Language :: Python :: 3
Classifier: Programming Language :: Python :: 3.6
Classifier: Programming Language :: Python :: 3.7
Classifier: License :: OSI Approved :: MIT License
Classifier: Operating System :: OS Independent
Requires-Python: >=2.7, <4
